messirve/__init__.py
messirve/__main__.py
messirve/analysis/__init__.py
messirve/analysis/analyzers/__init__.py
messirve/analysis/analyzers/base.py
messirve/analysis/analyzers/complexity.py
messirve/analysis/analyzers/coupling.py
messirve/analysis/analyzers/quality.py
messirve/analysis/analyzers/sonarqube.py
messirve/analysis/models.py
messirve/analysis/report.py
messirve/analysis/runner.py
messirve/analysis/storage.py
messirve/cli.py
messirve/config.py
messirve/context/__init__.py
messirve/context/detector.py
messirve/context/explorer.py
messirve/context/generator.py
messirve/context/models.py
messirve/engines/__init__.py
messirve/engines/base.py
messirve/engines/claude_code.py
messirve/exceptions.py
messirve/executor.py
messirve/feature_flags.py
messirve/git/__init__.py
messirve/git/manager.py
messirve/git/strategies.py
messirve/hooks/__init__.py
messirve/hooks/runner.py
messirve/hooks/types.py
messirve/logging/__init__.py
messirve/logging/console.py
messirve/logging/master_logger.py
messirve/logging/task_logger.py
messirve/models/__init__.py
messirve/models/config.py
messirve/models/execution.py
messirve/models/task.py
messirve/planning/__init__.py
messirve/planning/editor.py
messirve/planning/generator.py
messirve/planning/models.py
messirve/planning/session.py
messirve/task_sources/__init__.py
messirve/task_sources/base.py
messirve/task_sources/yaml_source.py
messirve/templates/__init__.py
messirve/templates/ai_ml.py
messirve/templates/basic.py
messirve-0.1.0.dist-info/METADATA
messirve-0.1.0.dist-info/WHEEL
messirve-0.1.0.dist-info/entry_points.txt
messirve-0.1.0.dist-info/licenses/LICENSE
messirve-0.1.0.dist-info/RECORD
