Metadata-Version: 2.4
Name: messirve
Version: 0.1.0
Summary: A CLI tool that orchestrates Claude Code to execute development tasks autonomously
License: MIT
License-File: LICENSE
Keywords: cli,automation,claude,development,tasks
Author: Messirve Team
Requires-Python: >=3.13,<4.0
Classifier: Development Status :: 4 - Beta
Classifier: Environment :: Console
Classifier: Intended Audience :: Developers
Classifier: License :: OSI Approved :: MIT License
Classifier: Operating System :: OS Independent
Classifier: Programming Language :: Python :: 3
Classifier: Programming Language :: Python :: 3.13
Classifier: Programming Language :: Python :: 3.14
Classifier: Topic :: Software Development :: Build Tools
Classifier: Topic :: Utilities
Requires-Dist: gitpython (>=3.1.0,<4.0.0)
Requires-Dist: pydantic (>=2.10.0,<3.0.0)
Requires-Dist: pyyaml (>=6.0.2,<7.0.0)
Requires-Dist: rich (>=13.9.0,<14.0.0)
Requires-Dist: ruamel-yaml (>=0.18.0,<0.19.0)
Requires-Dist: typer[all] (>=0.15.0,<0.16.0)
